pychopmarg/__init__.py
pychopmarg/__main__.py
pychopmarg/cli.py
pychopmarg/com.py
pychopmarg/common.py
pychopmarg/excel.py
pychopmarg/matlab.py
pychopmarg/noise.py
pychopmarg/optimize.py
pychopmarg/plot.py
pychopmarg/py.typed
pychopmarg/config/__init__.py
pychopmarg/config/ieee_8023by.py
pychopmarg/config/ieee_8023dj.py
pychopmarg/config/template.py
pychopmarg/utility/__init__.py
pychopmarg/utility/filter.py
pychopmarg/utility/general.py
pychopmarg/utility/jupyter.py
pychopmarg/utility/probability.py
pychopmarg/utility/sparams.py
pychopmarg-3.1.2.dist-info/licenses/LICENSE
pychopmarg-3.1.2.dist-info/METADATA
pychopmarg-3.1.2.dist-info/WHEEL
pychopmarg-3.1.2.dist-info/entry_points.txt
pychopmarg-3.1.2.dist-info/top_level.txt
pychopmarg-3.1.2.dist-info/RECORD
